cpc_api/__init__.py
cpc_api/__version.py
cpc_api/api.py
cpc_api-0.1.5.dist-info/DESCRIPTION.rst
cpc_api-0.1.5.dist-info/METADATA
cpc_api-0.1.5.dist-info/metadata.json
cpc_api-0.1.5.dist-info/RECORD
cpc_api-0.1.5.dist-info/top_level.txt
cpc_api-0.1.5.dist-info/WHEEL
