Metadata-Version: 2.0
Name: cpc-api
Version: 0.1.5
Summary: Python api for nosdeputes.fr and nossenateurs.fr
Home-page: https://github.com/regardscitoyens/cpc-api
Author: Regards Citoyens
Author-email: contact@regardscitoyens.org
License: MIT
Keywords: api nosdeputes.fr nossenateurs.fr
Platform: UNKNOWN
Classifier: Development Status :: 3 - Alpha
Classifier: License :: OSI Approved :: MIT License
Classifier: Operating System :: OS Independent
Classifier: Programming Language :: Python :: 2.7
Classifier: Programming Language :: Python :: 3
Requires-Dist: requests
Requires-Dist: fuzzywuzzy
